MOFF/MOFF.py
MOFF/MOFF_prediction.py
MOFF/__init__.py
MOFF/StaticFiles/GOP_model_3.h5
MOFF/StaticFiles/M1_matrix_dic_D9
MOFF/StaticFiles/M2_matrix_smooth_MLE
MOFF-1.2.4.data/scripts/MOFF
MOFF-1.2.4.dist-info/LICENSE
MOFF-1.2.4.dist-info/METADATA
MOFF-1.2.4.dist-info/WHEEL
MOFF-1.2.4.dist-info/top_level.txt
MOFF-1.2.4.dist-info/zip-safe
MOFF-1.2.4.dist-info/RECORD
