Metadata-Version: 2.1
Name: MOFF
Version: 1.2.4
Summary: Modular prediction of off-target effects for CRISPR/Cas9 system
Home-page: https://github.com/MDhewei/MOFF
Author: Wei He
Author-email: whe3@mdanderson.org
License: UNKNOWN
Platform: UNKNOWN
Requires-Dist: numpy
Requires-Dist: pandas
Requires-Dist: matplotlib
Requires-Dist: sklearn
Requires-Dist: argparse
Requires-Dist: seaborn
